{
  "days": {
    "Monday":    { "open": "09:00", "close": "18:00" },
    "Tuesday":   { "open": "09:00", "close": "18:00" },
    "Wednesday": { "open": "10:00", "close": "19:00" },
    "Thursday":  { "open": "10:00", "close": "21:00" },
    "Friday":    { "open": "09:00", "close": "21:00" },
    "Saturday":  { "open": "08:00", "close": "20:00" },
    "Sunday":    { "open": "10:00", "close": "17:00" }
  },
  "time_slots": [
    "07:00",
    "08:00",
    "09:00",
    "10:00",
    "12:00",
    "14:00",
    "16:00",
    "18:00",
    "20:00",
    "21:00"
  ]
}
